{
  "project_info": {
    "project_number": "122953494403",
    "project_id": "centro-espirita-online",
    "storage_bucket": "centro-espirita-online.firebasestorage.app"
  },
  "client": [
    {
      "client_info": {
        "mobilesdk_app_id": "1:122953494403:android:382cf9657b2e91302490b6",
        "android_client_info": {
          "package_name": "com.nicolasmenega.CEO"
        }
      },
      "oauth_client": [],
      "api_key": [
        {
          "current_key": "AIzaSyCA6ZEYnejJKRnP-Qfi-QpKGKv0ZDYFi0c"
        }
      ],
      "services": {
        "appinvite_service": {
          "other_platform_oauth_client": []
        }
      }
    },
    {
      "client_info": {
        "mobilesdk_app_id": "1:122953494403:android:62adb11b781a29312490b6",
        "android_client_info": {
          "package_name": "com.nicolasmenega.ceo"
        }
      },
      "oauth_client": [],
      "api_key": [
        {
          "current_key": "AIzaSyCA6ZEYnejJKRnP-Qfi-QpKGKv0ZDYFi0c"
        }
      ],
      "services": {
        "appinvite_service": {
          "other_platform_oauth_client": []
        }
      }
    }
  ],
  "configuration_version": "1"
}